after_class/__init__.py
after_class/metricians.py
after_class/plotting_tools.py
after_class/reporters.py
after_class/report_templates/basic_report.html
after_class/report_templates/worst_samples_report.html
after_class-0.0.24.dist-info/METADATA
after_class-0.0.24.dist-info/WHEEL
after_class-0.0.24.dist-info/top_level.txt
after_class-0.0.24.dist-info/RECORD
