Metadata-Version: 2.1
Name: after-class
Version: 0.0.24
Summary: Tool to analyze multiclassification ML models.
Home-page: https://github.com/streetbee/dv_after_class
Author: Moiseev Arseniy
Author-email: arseniy.moiseyev@phystech.edu
License: UNKNOWN
Platform: UNKNOWN
Classifier: Programming Language :: Python :: 3
Classifier: License :: OSI Approved :: MIT License
Classifier: Operating System :: OS Independent
Requires-Python: >=3.6
Requires-Dist: bs4
Requires-Dist: matplotlib (==3.3.2)
Requires-Dist: pandas (==1.1.3)
Requires-Dist: pickle5 (==0.0.11)
Requires-Dist: scikit-learn (==0.23.2)
